haystack/__init__.py
haystack/agent_recorder.py
haystack/binary_propagator.py
haystack/constants.py
haystack/http_recorder.py
haystack/propagator.py
haystack/recorder.py
haystack/span.py
haystack/span_pb2.py
haystack/text_propagator.py
haystack/tracer.py
haystack/util.py
haystack/agent/__init__.py
haystack/agent/spanAgent_pb2.py
haystack/agent/spanAgent_pb2_grpc.py
haystack_client-0.2.4.dist-info/LICENSE
haystack_client-0.2.4.dist-info/METADATA
haystack_client-0.2.4.dist-info/WHEEL
haystack_client-0.2.4.dist-info/top_level.txt
haystack_client-0.2.4.dist-info/RECORD
