Metadata-Version: 2.1
Name: haystack-client
Version: 0.2.4
Summary: Haystack Python OpenTracing Implementation
Home-page: https://github.com/ExpediaDotCom/haystack-client-python
Author: Ryan Hilfers, Haystack
Author-email: haystack@expediagroup.com
License: UNKNOWN
Keywords: opentracing,haystack,tracing,microservices,distributed
Platform: UNKNOWN
Classifier: Programming Language :: Python :: 3.5
Classifier: Programming Language :: Python :: 3.6
Classifier: Programming Language :: Python :: 3.7
Classifier: Programming Language :: Python :: 3.8
Classifier: Operating System :: OS Independent
Classifier: License :: OSI Approved :: Apache Software License
Requires-Python: >=3.5
Requires-Dist: opentracing (<3.0,>=2.3.0)
Requires-Dist: requests (<3.0,>=2.19)
Requires-Dist: requests-futures (<1.0,>=0.9.9)
Requires-Dist: protobuf (<4.0,>=3.11.2)
Requires-Dist: grpcio (<2.0,>=1.26.0)
